hotspotty_payment_email/__init__.py
hotspotty_payment_email/__main__.py
hotspotty_payment_email/cli.py
hotspotty_payment_email-0.4.0.dist-info/METADATA
hotspotty_payment_email-0.4.0.dist-info/WHEEL
hotspotty_payment_email-0.4.0.dist-info/entry_points.txt
hotspotty_payment_email-0.4.0.dist-info/RECORD
