Metadata-Version: 2.1
Name: hotspotty-payment-email
Version: 0.4.0
Summary: A command line tool that takes as input a list of commission reports in csv format exported from the [Commission report](https://app.hotspotty.net/workspace/helium/commission-reports) section of Hotspotty platform and send a gmail e-mail to each user inside the input reports to inform them about the rewards they'll receive.
Author: Andrea Del Corto
Author-email: andrea.delcorto@gmail.com
Requires-Python: >=3.8,<4.0
Classifier: Programming Language :: Python :: 3
Classifier: Programming Language :: Python :: 3.8
Classifier: Programming Language :: Python :: 3.9
Classifier: Programming Language :: Python :: 3.10
Classifier: Programming Language :: Python :: 3.11
Requires-Dist: click (>=8.1.3,<9.0.0)
Requires-Dist: google-api-python-client (>=2.86.0,<3.0.0)
Requires-Dist: google-auth-oauthlib (>=1.0.0,<2.0.0)
Requires-Dist: jinja2 (>=3.1.2,<4.0.0)
Requires-Dist: pandas (>=2.0.1,<3.0.0)
